epiagent/__init__.py
epiagent/dataset.py
epiagent/inference.py
epiagent/model.py
epiagent/preprocessing.py
epiagent/tokenization.py
epiagent/train.py
epiagent/utils.py
epiagent-0.0.3.dist-info/LICENSE
epiagent-0.0.3.dist-info/METADATA
epiagent-0.0.3.dist-info/WHEEL
epiagent-0.0.3.dist-info/top_level.txt
epiagent-0.0.3.dist-info/RECORD
