Metadata-Version: 2.1
Name: epiagent
Version: 0.0.3
Summary: Foundation model for single-cell epigenomic data.
Home-page: https://github.com/xy-chen16/EpiAgent
Author: Xiaoyang Chen
Author-email: xychen20@mails.tsinghua.edu.cn
Classifier: Programming Language :: Python :: 3
Classifier: License :: OSI Approved :: MIT License
Classifier: Operating System :: OS Independent
Requires-Python: >=3.8
License-File: LICENSE
Requires-Dist: numpy
Requires-Dist: pandas
Requires-Dist: scipy
Requires-Dist: scikit-learn
Requires-Dist: scanpy
Requires-Dist: torch (>=2.0.0)
Requires-Dist: transformers
Requires-Dist: anndata
Requires-Dist: POT (>=0.9.2)
Requires-Dist: faiss
Requires-Dist: flash-attn (>=2.5.7)
Provides-Extra: gpu
Requires-Dist: torch (>=2.0.0) ; extra == 'gpu'
Requires-Dist: flash-attn (>=2.5.7) ; extra == 'gpu'
